gbox/__init__.py
gbox/gboxmanager.py
gbox/data/__init__.py
gbox/data/dataaccessor.py
gbox/gpio/__init__.py
gbox/gpio/gpiomanager.py
GenergyGBox-0.1.1.dist-info/METADATA
GenergyGBox-0.1.1.dist-info/WHEEL
GenergyGBox-0.1.1.dist-info/top_level.txt
GenergyGBox-0.1.1.dist-info/RECORD
