Metadata-Version: 2.1
Name: GenergyGBox
Version: 0.1.1
Summary: GenergyBox
Home-page: UNKNOWN
Author: fengyi
License: MIT
Platform: UNKNOWN
Classifier: Programming Language :: Python
Classifier: Programming Language :: Python :: 3.9
Requires-Python: >=3.6
